pynibs/__init__.py
pynibs/coil.py
pynibs/freesurfer.py
pynibs/muap.py
pynibs/subject.py
pynibs/tensor_scaling.py
pynibs/tms_pulse.py
pynibs/congruence/__init__.py
pynibs/congruence/congruence.py
pynibs/congruence/ext_metrics.py
pynibs/congruence/stimulation_threshold.py
pynibs/data/configuration_exp0.yaml
pynibs/data/configuration_linear_MEP.yaml
pynibs/data/configuration_linear_RT.yaml
pynibs/data/configuration_sigmoid4.yaml
pynibs/data/network mapping configuration/configuration guide.md
pynibs/data/network mapping configuration/configuration_TEMPLATE.yaml
pynibs/data/network mapping configuration/configuration_for_testing.yaml
pynibs/data/network mapping configuration/configuration_modelTMS.yaml
pynibs/data/network mapping configuration/configuration_reg_isi_05.yaml
pynibs/data/network mapping configuration/output_documentation.md
pynibs/data/network mapping configuration/recommendations_for_accuracy_threshold.md
pynibs/data/neuron/models/L23_PC_cADpyr_biphasic_v1.csv
pynibs/data/neuron/models/L23_PC_cADpyr_monophasic_v1.csv
pynibs/data/neuron/models/L4_LBC_biphasic_v1.csv
pynibs/data/neuron/models/L4_LBC_monophasic_v1.csv
pynibs/data/neuron/models/L4_NBC_biphasic_v1.csv
pynibs/data/neuron/models/L4_NBC_monophasic_v1.csv
pynibs/data/neuron/models/L4_SBC_biphasic_v1.csv
pynibs/data/neuron/models/L4_SBC_monophasic_v1.csv
pynibs/data/neuron/models/L5_TTPC2_cADpyr_biphasic_v1.csv
pynibs/data/neuron/models/L5_TTPC2_cADpyr_monophasic_v1.csv
pynibs/expio/Mep.py
pynibs/expio/__init__.py
pynibs/expio/brainsight.py
pynibs/expio/brainvis.py
pynibs/expio/cobot.py
pynibs/expio/exp.py
pynibs/expio/fit_funs.py
pynibs/expio/localite.py
pynibs/expio/signal_ced.py
pynibs/expio/visor.py
pynibs/hdf5_io/__init__.py
pynibs/hdf5_io/hdf5_io.py
pynibs/hdf5_io/xdmf.py
pynibs/mesh/__init__.py
pynibs/mesh/mesh_struct.py
pynibs/mesh/transformations.py
pynibs/mesh/utils.py
pynibs/models/_TMS.py
pynibs/models/__init__.py
pynibs/neuron/__init__.py
pynibs/neuron/neuron_regression.py
pyNIBS-0.2024.8.dist-info/LICENSE
pyNIBS-0.2024.8.dist-info/METADATA
pyNIBS-0.2024.8.dist-info/WHEEL
pyNIBS-0.2024.8.dist-info/top_level.txt
pyNIBS-0.2024.8.dist-info/RECORD
