Metadata-Version: 2.1
Name: pyNIBS
Version: 0.2024.8
Summary: A python toolbox to conduct non-invasive brain stimulation (NIBS) experiments.
Author: Konstantin Weise, Ole Numssen, Benjamin Kalloch
Author-email: Konstantin Weise <weise@cbs.mpg.de>, Ole Numssen <numssen@cbs.mpg.de>, Benjamin Kallock <kalloch@cbs.mpg.de>
Maintainer-email: Konstantin Weise <weise@cbs.mpg.de>, Ole Numssen <numssen@cbs.mpg.de>
License: GNU GENERAL PUBLIC LICENSE
Project-URL: Home, https://gitlab.gwdg.de/tms-localization/pynibs
Project-URL: Docs, https://pynibs.readthedocs.io/
Project-URL: Twitter, https://www.twitter.com/num_ole
Project-URL: Download, https://pypi.org/project/pynibs/
Keywords: NIBS,non-invasive brain stimulation,TMS,FEM
Classifier: Development Status :: 3 - Alpha
Classifier: Intended Audience :: Science/Research
Classifier: Topic :: Scientific/Engineering
Classifier: Topic :: Software Development :: Build Tools
Classifier: Programming Language :: Python :: 3
Classifier: Programming Language :: Python :: 3.7
Classifier: Programming Language :: Python :: 3.9
Requires-Python: >=3.7
License-File: LICENSE
Requires-Dist: cython >=0.29.20
Requires-Dist: h5py >=2.10.0
Requires-Dist: lmfit
Requires-Dist: matplotlib >=3.2.1
Requires-Dist: meshio
Requires-Dist: nibabel >=3.0.2
Requires-Dist: nilearn >=0.6.2
Requires-Dist: numpy <=2.0.0
Requires-Dist: ortools <=9.1.9490
Requires-Dist: pandas >=1.0.3
Requires-Dist: pyyaml >=5.3.1
Requires-Dist: scikit-learn >=0.22.1
Requires-Dist: scipy >=1.4.1
Requires-Dist: scikit-image
Requires-Dist: setuptools >=49.1.0
Requires-Dist: tqdm >=4.45.0
Requires-Dist: trimesh >=3.8.11
Requires-Dist: tvb-gdist
Requires-Dist: fslpy
Requires-Dist: uncertainties
Requires-Dist: asteval
Requires-Dist: jsonschema
Requires-Dist: tables
Requires-Dist: vtk
Requires-Dist: fmm3dpy
